{
  "name": "t:sections.header.name",
  "type": "header",
  "sections": {
    "header": {
      "type": "header",
      "disabled": true,
      "settings": {
        "logo_position": "middle-left",
        "menu": "main-menu",
        "menu_type_desktop": "dropdown",
        "sticky_header_type": "on-scroll-up",
        "show_line_separator": true,
        "color_scheme": "background-1",
        "menu_color_scheme": "",
        "enable_country_selector": true,
        "enable_language_selector": true,
        "mobile_logo_position": "center",
        "margin_bottom": 0,
        "padding_top": 20,
        "padding_bottom": 20
      }
    },
    "discount-bar": {
      "type": "discount-bar",
      "blocks": {
        "be74d7f9-9548-4ae3-9575-f97d27db05fb": {
          "type": "discount",
          "settings": {
            "text": "<p><strong>SPECIAL OFFER: SALE UP TO 60% OFF. USE CODE: “SALE70”<\/strong><\/p>",
            "bg_color": "#d6fd8b",
            "text_color": "#000000"
          }
        }
      },
      "block_order": [
        "be74d7f9-9548-4ae3-9575-f97d27db05fb"
      ],
      "settings": {
        "text_align": "text-center"
      }
    },
    "header-new": {
      "type": "header-new"
    },
    "collections-bar": {
      "type": "collections-bar",
      "settings": {
        "text_align": "text-left"
      }
    }
  },
  "order": [
    "header",
    "discount-bar",
    "header-new",
    "collections-bar"
  ]
}
